import_transforms/__init__.py
import_transforms/__main__.py
import_transforms-0.6.1.dist-info/LICENSE
import_transforms-0.6.1.dist-info/METADATA
import_transforms-0.6.1.dist-info/WHEEL
import_transforms-0.6.1.dist-info/RECORD
