Metadata-Version: 2.1
Name: import-transforms
Version: 0.6.1
Summary: 
License: MIT
Author: Adam Hupp
Author-email: adam@hupp.org
Requires-Python: >=3.8,<4.0
Classifier: License :: OSI Approved :: MIT License
Classifier: Programming Language :: Python :: 3
Classifier: Programming Language :: Python :: 3.8
Classifier: Programming Language :: Python :: 3.9
Classifier: Programming Language :: Python :: 3.10
Classifier: Programming Language :: Python :: 3.11
